expat/__init__.py
expat/api.py
expat/config.py
expat/exceptions.py
expat/utils.py
expat/db/__init__.py
expat/db/init_schema.py
expat/db/migration.py
expat-0.1.0.post4.dist-info/METADATA
expat-0.1.0.post4.dist-info/WHEEL
expat-0.1.0.post4.dist-info/entry_points.txt
expat-0.1.0.post4.dist-info/RECORD
