Metadata-Version: 2.4
Name: expat
Version: 0.1.0.post4
Summary: Add your description here
Author-email: William Strausser <william.e.strausser@gmail.com>
Requires-Python: >=3.13
Requires-Dist: pydantic>=2.11.7
